pentinsula/__init__.py
pentinsula/chunkbuffer.py
pentinsula/h5utils.py
pentinsula/timeseries.py
pentinsula/types.py
pentinsula-0.1.dist-info/LICENSE
pentinsula-0.1.dist-info/METADATA
pentinsula-0.1.dist-info/WHEEL
pentinsula-0.1.dist-info/top_level.txt
pentinsula-0.1.dist-info/RECORD
