Metadata-Version: 2.1
Name: pentinsula
Version: 0.1
Summary: h5py utilities for time series data in HDF5
Home-page: https://github.com/jl-wynen/pentinsula
Author: Jan-Lukas Wynen
Author-email: j-l.wynen@hotmail.de
License: MIT
Project-URL: Source Code, https://github.com/jl-wynen/pentinsula
Keywords: hdf5 time_series h5py
Platform: UNKNOWN
Classifier: License :: OSI Approved :: MIT License
Classifier: Programming Language :: Python :: 3 :: Only
Classifier: Programming Language :: Python :: 3.6
Classifier: Programming Language :: Python :: 3.7
Classifier: Programming Language :: Python :: 3.8
Classifier: Intended Audience :: Developers
Classifier: Intended Audience :: Science/Research
Classifier: Topic :: Scientific/Engineering
Classifier: Topic :: Software Development :: Libraries :: Python Modules
Requires-Python: >=3.6
Requires-Dist: h5py
Requires-Dist: numpy
